{
    "data": [
        {
            "name": "重庆日报官方微信",
            "accountUnit": "重庆日报",
            "accountType": "财经",
            "headPicUrl": "http://img5.imgtn.bdimg.com/it/u=3494656842,1664655621&fm=21&gp=0.jpg",
            "authType": "官方",
            "vipLevel": "vip1",
            "weiboId": "dj-love-ysl",
            "content": "[话筒]假期必备！80个超实用电话号码】手机丢了，解绑支付宝打什么电话？收到诈骗短信，如何举报？出国旅游遇到人身安全受侵害，怎么打电话求助？消费投诉要找谁……元旦假期将过，农历春节就在眼前，超实用电话大全↓↓不论是宅在家，还是出门旅游，总有一个用得上！速速转发收藏！@人民日报",
            "crtime": "10月19日 9：30",
            "source": "红米手机",
            "commentNum": "1118",
            "forwardNum": "1118",
            "likesNum": "1118"
        },
        {
            "name": "重庆日报官方微信",
            "accountUnit": "重庆日报",
            "accountType": "财经",
            "headPicUrl": "http://img5.imgtn.bdimg.com/it/u=3494656842,1664655621&fm=21&gp=0.jpg",
            "authType": "官方",
            "vipLevel": "vip1",
            "weiboId": "dj-love-ysl",
            "content": "此前澎湃客户端今日推送新闻称，江西九江浔阳区发生6.9级地震。此信息为地震台网自动后台录入信息，后经编辑人工核实，此信息不实，向各位用户致歉。",
            "crtime": "10月19日 9：30",
            "source": "红米手机",
            "commentNum": "1118",
            "forwardNum": "1118",
            "likesNum": "1118"
        },
        {
            "name": "重庆日报官方微信",
            "accountUnit": "重庆日报",
            "accountType": "财经",
            "headPicUrl": "http://img5.imgtn.bdimg.com/it/u=3494656842,1664655621&fm=21&gp=0.jpg",
            "authType": "官方",
            "vipLevel": "vip1",
            "weiboId": "dj-love-ysl",
            "content": "强烈建议今天交易不算，恢复到今天开盘前状态，重审熔断机制，给市场公平的交易环境。",
            "crtime": "10月19日 9：30",
            "source": "红米手机",
            "commentNum": "1118",
            "forwardNum": "1118",
            "likesNum": "1118"
        }
    ]
}